<?xml version="1.0" encoding="utf-8"?><SkyImageIndexesStatsData xmlns:xsd="http://www.w3.org/2001/XMLSchema" xmlns:xsi="http://www.w3.org/2001/XMLSchema-instance"><FileName>D:\_gulevlab\SkyImagesAnalysis\_DBGbin\snapshots\img-2016-01-14T12-36-30devID2.jpg</FileName><grixStatsData><varname>GrIx</varname><FileName>D:\_gulevlab\SkyImagesAnalysis\_DBGbin\snapshots\img-2016-01-14T12-36-30devID2.jpg</FileName><lTplFieldPercentiles><FieldPercentileValue><percIndex>5</percIndex><percValue>0.6404827411139089</percValue></FieldPercentileValue><FieldPercentileValue><percIndex>10</percIndex><percValue>0.65746195242030936</percValue></FieldPercentileValue><FieldPercentileValue><percIndex>15</percIndex><percValue>0.67359423795469353</percValue></FieldPercentileValue><FieldPercentileValue><percIndex>20</percIndex><percValue>0.69138178212849177</percValue></FieldPercentileValue><FieldPercentileValue><percIndex>25</percIndex><percValue>0.71044726757107324</percValue></FieldPercentileValue><FieldPercentileValue><percIndex>30</percIndex><percValue>0.73007606963829041</percValue></FieldPercentileValue><FieldPercentileValue><percIndex>35</percIndex><percValue>0.75280452452465285</percValue></FieldPercentileValue><FieldPercentileValue><percIndex>40</percIndex><percValue>0.77860017247724822</percValue></FieldPercentileValue><FieldPercentileValue><percIndex>45</percIndex><percValue>0.80674843046033873</percValue></FieldPercentileValue><FieldPercentileValue><percIndex>50</percIndex><percValue>0.83437194717841712</percValue></FieldPercentileValue><FieldPercentileValue><percIndex>55</percIndex><percValue>0.86158631207441938</percValue></FieldPercentileValue><FieldPercentileValue><percIndex>60</percIndex><percValue>0.88042256237150263</percValue></FieldPercentileValue><FieldPercentileValue><percIndex>65</percIndex><percValue>0.89472202343409368</percValue></FieldPercentileValue><FieldPercentileValue><percIndex>70</percIndex><percValue>0.90603247878740367</percValue></FieldPercentileValue><FieldPercentileValue><percIndex>75</percIndex><percValue>0.91552982188669108</percValue></FieldPercentileValue><FieldPercentileValue><percIndex>80</percIndex><percValue>0.9260300912917272</percValue></FieldPercentileValue><FieldPercentileValue><percIndex>85</percIndex><percValue>0.93751426844195518</percValue></FieldPercentileValue><FieldPercentileValue><percIndex>90</percIndex><percValue>0.94949834790615062</percValue></FieldPercentileValue><FieldPercentileValue><percIndex>95</percIndex><percValue>0.96330591693214418</percValue></FieldPercentileValue><FieldPercentileValue><percIndex>100</percIndex><percValue>1</percValue></FieldPercentileValue></lTplFieldPercentiles><min>-3.57929864140146</min><max>1</max><mean>0.81331606860088435</mean><variance>0.013808338010871299</variance><stdev>0.11750888481672907</stdev><skewness>-0.61795924471671293</skewness><kurtosis>0.983785516911812</kurtosis><rms>0.82176113386248362</rms></grixStatsData><brightnessStatsData><varname>Brightness</varname><FileName>D:\_gulevlab\SkyImagesAnalysis\_DBGbin\snapshots\img-2016-01-14T12-36-30devID2.jpg</FileName><lTplFieldPercentiles><FieldPercentileValue><percIndex>5</percIndex><percValue>54.015377665271473</percValue></FieldPercentileValue><FieldPercentileValue><percIndex>10</percIndex><percValue>74.224793315462563</percValue></FieldPercentileValue><FieldPercentileValue><percIndex>15</percIndex><percValue>78.183622840248731</percValue></FieldPercentileValue><FieldPercentileValue><percIndex>20</percIndex><percValue>82.757799567416342</percValue></FieldPercentileValue><FieldPercentileValue><percIndex>25</percIndex><percValue>88.092639751257849</percValue></FieldPercentileValue><FieldPercentileValue><percIndex>30</percIndex><percValue>93.982905581475251</percValue></FieldPercentileValue><FieldPercentileValue><percIndex>35</percIndex><percValue>98.779384715120528</percValue></FieldPercentileValue><FieldPercentileValue><percIndex>40</percIndex><percValue>103.69053560788866</percValue></FieldPercentileValue><FieldPercentileValue><percIndex>45</percIndex><percValue>109.37754192602209</percValue></FieldPercentileValue><FieldPercentileValue><percIndex>50</percIndex><percValue>114.27568586736267</percValue></FieldPercentileValue><FieldPercentileValue><percIndex>55</percIndex><percValue>117.68096570923164</percValue></FieldPercentileValue><FieldPercentileValue><percIndex>60</percIndex><percValue>120.71676701429101</percValue></FieldPercentileValue><FieldPercentileValue><percIndex>65</percIndex><percValue>123.8717277792131</percValue></FieldPercentileValue><FieldPercentileValue><percIndex>70</percIndex><percValue>127.73514457334701</percValue></FieldPercentileValue><FieldPercentileValue><percIndex>75</percIndex><percValue>133.06348489784568</percValue></FieldPercentileValue><FieldPercentileValue><percIndex>80</percIndex><percValue>140.24899988132887</percValue></FieldPercentileValue><FieldPercentileValue><percIndex>85</percIndex><percValue>149.31462516052983</percValue></FieldPercentileValue><FieldPercentileValue><percIndex>90</percIndex><percValue>163.83262541983603</percValue></FieldPercentileValue><FieldPercentileValue><percIndex>95</percIndex><percValue>195.73022013226975</percValue></FieldPercentileValue><FieldPercentileValue><percIndex>100</percIndex><percValue>254.99999999999997</percValue></FieldPercentileValue></lTplFieldPercentiles><min>2.4934</min><max>255</max><mean>115.19570595462841</mean><variance>1659.7317859025952</variance><stdev>40.739805913904341</stdev><skewness>0.699017859795631</skewness><kurtosis>1.3804891080467203</kurtosis><rms>122.18748682266205</rms></brightnessStatsData><rStatsData><varname>Rchannel</varname><FileName>D:\_gulevlab\SkyImagesAnalysis\_DBGbin\snapshots\img-2016-01-14T12-36-30devID2.jpg</FileName><lTplFieldPercentiles><FieldPercentileValue><percIndex>5</percIndex><percValue>71</percValue></FieldPercentileValue><FieldPercentileValue><percIndex>10</percIndex><percValue>105</percValue></FieldPercentileValue><FieldPercentileValue><percIndex>15</percIndex><percValue>112</percValue></FieldPercentileValue><FieldPercentileValue><percIndex>20</percIndex><percValue>117</percValue></FieldPercentileValue><FieldPercentileValue><percIndex>25</percIndex><percValue>122</percValue></FieldPercentileValue><FieldPercentileValue><percIndex>30</percIndex><percValue>127</percValue></FieldPercentileValue><FieldPercentileValue><percIndex>35</percIndex><percValue>131</percValue></FieldPercentileValue><FieldPercentileValue><percIndex>40</percIndex><percValue>134</percValue></FieldPercentileValue><FieldPercentileValue><percIndex>45</percIndex><percValue>137</percValue></FieldPercentileValue><FieldPercentileValue><percIndex>50</percIndex><percValue>140</percValue></FieldPercentileValue><FieldPercentileValue><percIndex>55</percIndex><percValue>142</percValue></FieldPercentileValue><FieldPercentileValue><percIndex>60</percIndex><percValue>145</percValue></FieldPercentileValue><FieldPercentileValue><percIndex>65</percIndex><percValue>147</percValue></FieldPercentileValue><FieldPercentileValue><percIndex>70</percIndex><percValue>151</percValue></FieldPercentileValue><FieldPercentileValue><percIndex>75</percIndex><percValue>155</percValue></FieldPercentileValue><FieldPercentileValue><percIndex>80</percIndex><percValue>161</percValue></FieldPercentileValue><FieldPercentileValue><percIndex>85</percIndex><percValue>169</percValue></FieldPercentileValue><FieldPercentileValue><percIndex>90</percIndex><percValue>182</percValue></FieldPercentileValue><FieldPercentileValue><percIndex>95</percIndex><percValue>205</percValue></FieldPercentileValue><FieldPercentileValue><percIndex>100</percIndex><percValue>255</percValue></FieldPercentileValue></lTplFieldPercentiles><min>0</min><max>255</max><mean>139.076425408454</mean><variance>1420.0146543498608</variance><stdev>37.6830818053654</stdev><skewness>-0.1305902288607155</skewness><kurtosis>1.927643909020085</kurtosis><rms>144.09117361460287</rms></rStatsData><gStatsData><varname>Gchannel</varname><FileName>D:\_gulevlab\SkyImagesAnalysis\_DBGbin\snapshots\img-2016-01-14T12-36-30devID2.jpg</FileName><lTplFieldPercentiles><FieldPercentileValue><percIndex>5</percIndex><percValue>44</percValue></FieldPercentileValue><FieldPercentileValue><percIndex>10</percIndex><percValue>62</percValue></FieldPercentileValue><FieldPercentileValue><percIndex>15</percIndex><percValue>65</percValue></FieldPercentileValue><FieldPercentileValue><percIndex>20</percIndex><percValue>70</percValue></FieldPercentileValue><FieldPercentileValue><percIndex>25</percIndex><percValue>76</percValue></FieldPercentileValue><FieldPercentileValue><percIndex>30</percIndex><percValue>81</percValue></FieldPercentileValue><FieldPercentileValue><percIndex>35</percIndex><percValue>87</percValue></FieldPercentileValue><FieldPercentileValue><percIndex>40</percIndex><percValue>93</percValue></FieldPercentileValue><FieldPercentileValue><percIndex>45</percIndex><percValue>100</percValue></FieldPercentileValue><FieldPercentileValue><percIndex>50</percIndex><percValue>105</percValue></FieldPercentileValue><FieldPercentileValue><percIndex>55</percIndex><percValue>110</percValue></FieldPercentileValue><FieldPercentileValue><percIndex>60</percIndex><percValue>114</percValue></FieldPercentileValue><FieldPercentileValue><percIndex>65</percIndex><percValue>118</percValue></FieldPercentileValue><FieldPercentileValue><percIndex>70</percIndex><percValue>122</percValue></FieldPercentileValue><FieldPercentileValue><percIndex>75</percIndex><percValue>128</percValue></FieldPercentileValue><FieldPercentileValue><percIndex>80</percIndex><percValue>136</percValue></FieldPercentileValue><FieldPercentileValue><percIndex>85</percIndex><percValue>146</percValue></FieldPercentileValue><FieldPercentileValue><percIndex>90</percIndex><percValue>160</percValue></FieldPercentileValue><FieldPercentileValue><percIndex>95</percIndex><percValue>195</percValue></FieldPercentileValue><FieldPercentileValue><percIndex>100</percIndex><percValue>255</percValue></FieldPercentileValue></lTplFieldPercentiles><min>0</min><max>255</max><mean>107.32752116519619</mean><variance>1922.0554087566381</variance><stdev>43.841252363004394</stdev><skewness>0.79733115550555023</skewness><kurtosis>1.1088033015898586</kurtosis><rms>115.93641190647047</rms></gStatsData><bStatsData><varname>Bchannel</varname><FileName>D:\_gulevlab\SkyImagesAnalysis\_DBGbin\snapshots\img-2016-01-14T12-36-30devID2.jpg</FileName><lTplFieldPercentiles><FieldPercentileValue><percIndex>5</percIndex><percValue>43</percValue></FieldPercentileValue><FieldPercentileValue><percIndex>10</percIndex><percValue>52</percValue></FieldPercentileValue><FieldPercentileValue><percIndex>15</percIndex><percValue>56</percValue></FieldPercentileValue><FieldPercentileValue><percIndex>20</percIndex><percValue>60</percValue></FieldPercentileValue><FieldPercentileValue><percIndex>25</percIndex><percValue>66</percValue></FieldPercentileValue><FieldPercentileValue><percIndex>30</percIndex><percValue>71</percValue></FieldPercentileValue><FieldPercentileValue><percIndex>35</percIndex><percValue>77</percValue></FieldPercentileValue><FieldPercentileValue><percIndex>40</percIndex><percValue>83</percValue></FieldPercentileValue><FieldPercentileValue><percIndex>45</percIndex><percValue>89</percValue></FieldPercentileValue><FieldPercentileValue><percIndex>50</percIndex><percValue>95</percValue></FieldPercentileValue><FieldPercentileValue><percIndex>55</percIndex><percValue>101</percValue></FieldPercentileValue><FieldPercentileValue><percIndex>60</percIndex><percValue>105</percValue></FieldPercentileValue><FieldPercentileValue><percIndex>65</percIndex><percValue>110</percValue></FieldPercentileValue><FieldPercentileValue><percIndex>70</percIndex><percValue>114</percValue></FieldPercentileValue><FieldPercentileValue><percIndex>75</percIndex><percValue>119</percValue></FieldPercentileValue><FieldPercentileValue><percIndex>80</percIndex><percValue>127</percValue></FieldPercentileValue><FieldPercentileValue><percIndex>85</percIndex><percValue>137</percValue></FieldPercentileValue><FieldPercentileValue><percIndex>90</percIndex><percValue>152</percValue></FieldPercentileValue><FieldPercentileValue><percIndex>95</percIndex><percValue>184</percValue></FieldPercentileValue><FieldPercentileValue><percIndex>100</percIndex><percValue>255</percValue></FieldPercentileValue></lTplFieldPercentiles><min>0</min><max>255</max><mean>98.44493632339173</mean><variance>1875.4350210802847</variance><stdev>43.306293088652659</stdev><skewness>0.97361732422411584</skewness><kurtosis>1.382540148395994</kurtosis><rms>107.54924416719088</rms></bStatsData></SkyImageIndexesStatsData>